conec/__init__.py
conec/context2vec.py
conec/word2vec.py
conec-2.0.1.dist-info/LICENSE
conec-2.0.1.dist-info/METADATA
conec-2.0.1.dist-info/WHEEL
conec-2.0.1.dist-info/top_level.txt
conec-2.0.1.dist-info/RECORD
