Metadata-Version: 2.1
Name: conec
Version: 2.0.1
Summary: Context Encoders (ConEc) as an extension of word2vec
Home-page: https://github.com/cod3licious/conec
Author: cod3licious
Author-email: cod3licious@gmail.com
License: MIT
Keywords: context encoders word embeddings word2vec
Platform: UNKNOWN
Classifier: Development Status :: 3 - Alpha
Classifier: Intended Audience :: Science/Research
Classifier: Topic :: Scientific/Engineering :: Artificial Intelligence
Classifier: License :: OSI Approved :: MIT License
Classifier: Programming Language :: Python :: 2
Classifier: Programming Language :: Python :: 2.7
Classifier: Programming Language :: Python :: 3
Classifier: Programming Language :: Python :: 3.4
Classifier: Programming Language :: Python :: 3.5
Requires-Dist: future
Requires-Dist: numpy
Requires-Dist: scipy
